pyconll/__init__.py
pyconll/_compile.py
pyconll/_ir.py
pyconll/_version
pyconll/conllu.py
pyconll/exception.py
pyconll/format.py
pyconll/py.typed
pyconll/schema.py
pyconll/shared.py
pyconll/tree.py
pyconll-4.0.0.dist-info/licenses/LICENSE
pyconll-4.0.0.dist-info/METADATA
pyconll-4.0.0.dist-info/WHEEL
pyconll-4.0.0.dist-info/top_level.txt
pyconll-4.0.0.dist-info/RECORD
