Metadata-Version: 2.4
Name: pyconll
Version: 4.0.0
Summary: Read and manipulate CoNLL files
Author-email: Matias Grioni <matgrioni@gmail.com>
License-Expression: MIT
Project-URL: homepage, https://pyconll.github.io
Project-URL: source, https://github.com/pyconll/pyconll
Project-URL: documentation, https://pyconll.readthedocs.io/en/stable/
Keywords: nlp,conllu,conll,universal dependencies
Classifier: Development Status :: 5 - Production/Stable
Classifier: Intended Audience :: Developers
Classifier: Intended Audience :: Education
Classifier: Intended Audience :: Science/Research
Classifier: Programming Language :: Python :: 3 :: Only
Classifier: Programming Language :: Python :: Implementation :: CPython
Classifier: Topic :: Scientific/Engineering
Classifier: Topic :: Utilities
Requires-Python: ~=3.14
License-File: LICENSE
Dynamic: license-file
